{
  "citations": [
    {
      "auteur": "Joueur du Grenier",
      "citation": "La France : bloque l'&ccès a certain sites ..* -Est ce que vous connaissez NordVPN ?"
    },
    {
      "auteur" : "Denis Brognard",
      "citation" : "HAA"
    },
    {
      "auteur" : "Rick Astley",
      "citation" : "Never gonna give you up !"
    },
    {
      "auteur" : "Frank Lebœuf",
      "citation" : "Allez sur vendezvotrevoiture.fr"
    },
    {
      "auteur" : "Bigflo",
      "citation" : "Ça n'a rrrrrrrrien à voir"
    },
    {
      "auteur" : "Brice de nice",
      "citation" : "Casséééééééééééééééééééé"
    },
    {
      "auteur": "Another random minecraft villager",
      "citation": "Hmm"
    },
    {
      "auteur": "a random minecraft villager",
      "citation": "Hmm"
    },
    {
      "auteur": "Feldup",
      "citation": "Aujourd'hui petit finding de 4H, j'espère qui va vous plaire"
    },
    {
      "auteur": "Gartin59",
      "citation": "JE SUIS LE GOOOOOAT DES ECHECS"
    },
    {
      "auteur": "Hakita",
      "citation": "if you want to worry about something looking bad. Go check out the nearest mirror."
    },
    {
      "auteur": "Inoxtag",
      "citation": "A chacun son Everst, à chacun son propre rêve. Il n'y a pas de grands ou de petits rêve. L'important c'est simplement d'essayer de devenir meilleur qu'hier. Et les plus grandes avenures se vivent toujours à plusieurs, rien ne se fait seul."
    },
    {
        "auteur" : "Julien song",
        "citation" : "Je le voit arriver avec ces gros sabots.."
    },
    {
        "auteur" : "FuzeIII",
        "citation" : "On m'appelle FuzeIII, TutututuuTU"
    },
    {
        "auteur" : "Yvan Monka",
        "citation" : "Bonjour, dans cette vidéo tu vas apprendre a ..."
    },
    {
        "auteur" : "Minos prime",
        "citation": "JUGDEMENT"
    },
    {
        "auteur" : "Sisyphus prime",
        "citation" : "Hmm, a visitor"
    },
    {
        "auteur" : "Gabriel",
        "citation" : "Turn back machine.."
    },
    {
        "auteur" : "Paul mirabel",
        "citation" : "Salam les royaux"
    },
    {
      "auteur" : "Théobabac",
      "citation" : "Tu es triste ? \n Arrete."
    },
    {
      "auteur" : "random arch user",
      "citation" : "I use Arch btw."
    },
    {
      "auteur" : "Billy",
      "citation" : "Les moutons font des oeuf, mais t'es con ou quoi tu vois bien que les nuages aussi tombent pas sa s'appelle la gravité espece de con"
    },
    { 
      "auteur" : "Scatman",
      "citation" : "SKI-BI DIBBY DIB YO DA DUB DUB YO DA DUB DUB"
    }

  ]
}
